LICENSE
MANIFEST.in
README.md
setup.py
algaestat/__init__.py
algaestat/example.py
algaestat/example2.py
algaestat.egg-info/PKG-INFO
algaestat.egg-info/SOURCES.txt
algaestat.egg-info/dependency_links.txt
algaestat.egg-info/requires.txt
algaestat.egg-info/top_level.txt
algaestat/io/__init__.py
algaestat/io/config.json
algaestat/io/dynamo.py
algaestat/utils/__init__.py
algaestat/utils/aggregate.py