Metadata-Version: 2.1
Name: algaestat
Version: 1.0.2
Summary: Algae cultivating data extract-transform-load package
Home-page: https://azcati.asu.edu/
Author: David A. Baker
Classifier: Intended Audience :: Manufacturing 
Classifier: License :: Other/Proprietary License
Classifier: Programming Language :: Python :: 3 :: Only
Requires-Python: >3.10.0
License-File: LICENSE
Requires-Dist: pandas
Requires-Dist: boto3
Requires-Dist: simplejson
Requires-Dist: csaps
Requires-Dist: importlib_resources
Requires-Dist: numpy
